pvlab/__init__.py
pvlab/dataframes/__init__.py
pvlab/dataframes/dfdicts.py
pvlab/doc/Makefile
pvlab/doc/make.bat
pvlab/doc/requirements.txt
pvlab/doc/build/genindex.html
pvlab/doc/build/index.html
pvlab/doc/build/objects.inv
pvlab/doc/build/py-modindex.html
pvlab/doc/build/search.html
pvlab/doc/build/searchindex.js
pvlab/doc/build/_sources/index.rst.txt
pvlab/doc/build/_sources/usage/en/LICENSE.txt
pvlab/doc/build/_sources/usage/en/README.txt
pvlab/doc/build/_sources/usage/en/installation.rst.txt
pvlab/doc/build/_sources/usage/en/overview.rst.txt
pvlab/doc/build/_sources/usage/en/preface.rst.txt
pvlab/doc/build/_sources/usage/en/tools.rst.txt
pvlab/doc/build/_sources/usage/en/tools_dataframes.rst.txt
pvlab/doc/build/_sources/usage/en/tools_math.rst.txt
pvlab/doc/build/_sources/usage/en/whats_new.rst.txt
pvlab/doc/build/_sources/usage/en/whatsnew.rst.txt
pvlab/doc/build/_sources/usage/en/releases/v0.1.0.txt
pvlab/doc/build/_static/alabaster.css
pvlab/doc/build/_static/basic.css
pvlab/doc/build/_static/custom.css
pvlab/doc/build/_static/doctools.js
pvlab/doc/build/_static/documentation_options.js
pvlab/doc/build/_static/file.png
pvlab/doc/build/_static/jquery-3.5.1.js
pvlab/doc/build/_static/jquery.js
pvlab/doc/build/_static/language_data.js
pvlab/doc/build/_static/minus.png
pvlab/doc/build/_static/plus.png
pvlab/doc/build/_static/pygments.css
pvlab/doc/build/_static/searchtools.js
pvlab/doc/build/_static/underscore-1.13.1.js
pvlab/doc/build/_static/underscore.js
pvlab/doc/build/usage/en/LICENSE.html
pvlab/doc/build/usage/en/README.html
pvlab/doc/build/usage/en/installation.html
pvlab/doc/build/usage/en/overview.html
pvlab/doc/build/usage/en/preface.html
pvlab/doc/build/usage/en/tools.html
pvlab/doc/build/usage/en/tools_dataframes.html
pvlab/doc/build/usage/en/tools_math.html
pvlab/doc/build/usage/en/whats_new.html
pvlab/doc/build/usage/en/whatsnew.html
pvlab/doc/build/usage/en/releases/v0.1.0.html
pvlab/doc/source/conf.py
pvlab/doc/source/index.rst
pvlab-0.1.0.dev7.dist-info/LICENSE.txt
pvlab-0.1.0.dev7.dist-info/WHEEL
pvlab-0.1.0.dev7.dist-info/METADATA
pvlab-0.1.0.dev7.dist-info/RECORD
