Metadata-Version: 2.1
Name: pvlab
Version: 0.1.0.dev7
Summary: The package ``pvlab``provides tools for solar sensors and pv devices.
Author-email: "Jose P. Silva" <josepedro.silva@ciemat.es>
Classifier: License :: OSI Approved :: BSD License
